bignmf/__init__.py
bignmf/datasets/SimulatedX1.csv
bignmf/datasets/SimulatedX2.csv
bignmf/datasets/SimulatedX3.csv
bignmf/datasets/__init__.py
bignmf/datasets/datasets.py
bignmf/models/__init__.py
bignmf/models/nmf.py
bignmf/models/jnmf/__init__.py
bignmf/models/jnmf/integrative.py
bignmf/models/jnmf/jnmf_base.py
bignmf/models/jnmf/standard.py
bignmf/models/snmf/__init__.py
bignmf/models/snmf/snmf_base.py
bignmf/models/snmf/sparse.py
bignmf/models/snmf/standard.py
bignmf-1.0.5.dist-info/METADATA
bignmf-1.0.5.dist-info/RECORD
bignmf-1.0.5.dist-info/WHEEL
bignmf-1.0.5.dist-info/top_level.txt
