Metadata-Version: 2.1
Name: bignmf
Version: 1.0.5
Summary: Non-negative matrix factorization
Home-page: https://github.com/thenmf/bignmf
Author: Haran Rajkumar, Vaibhav Kulshrestha
Author-email: haranrajkumar97@gmail.com, vaibhav1kulshrestha@gmail.com
License: UNKNOWN
Platform: UNKNOWN
Classifier: Programming Language :: Python :: 3
Classifier: License :: OSI Approved :: MIT License
Classifier: Operating System :: OS Independent
Requires-Dist: numpy
Requires-Dist: pandas
Requires-Dist: fastcluster
Requires-Dist: scipy
